math_genie_calc/__init__.py
math_genie_calc/__main__.py
math_genie_calc/math_genie_calc_mcp_server_v1.py
math_genie_calc-0.1.8.dist-info/METADATA
math_genie_calc-0.1.8.dist-info/WHEEL
math_genie_calc-0.1.8.dist-info/entry_points.txt
math_genie_calc-0.1.8.dist-info/RECORD
