Metadata-Version: 2.4
Name: math_genie_calc
Version: 0.1.8
Summary: math genie calculator
Requires-Python: >=3.10
Requires-Dist: build>=1.2.2.post1
Requires-Dist: mcp>=1.12.1
Requires-Dist: twine>=6.1.0
